{
  "symbol": "BTOG",
  "timestamp": "2025-07-21T15:10:00",
  "current_price": 0.7465,
  "orb_high": 0.925,
  "orb_low": 0.85,
  "orb_range": 0.07500000000000007,
  "orb_midpoint": 0.8875,
  "breakout_type": "bearish_breakdown",
  "breakout_percentage": 12.176470588235286,
  "volume_ratio": 1.545901707105361,
  "confidence_score": 0.8114048234923815,
  "priority": "MEDIUM",
  "confidence_level": "HIGH",
  "recommended_stop_loss": 0.8024875,
  "recommended_take_profit": 0.71664,
  "alert_message": "[15:10:00] ORB ALERT: BTOG \u2193 $0.75 (+12.18% vs ORB Low)\nVolume: 1.5x avg | Confidence: 0.81 | Priority: MEDIUM | EMA9: $0.75 | EMA20: $0.76 | EMA9\u2193EMA20 | Div: -0.7%\nStop: $0.80 | Target: $0.72",
  "ema_9": 0.7503923021377514,
  "ema_20": 0.7557544242356827,
  "ema_9_above_20": false,
  "ema_9_below_20": true,
  "ema_divergence": -0.0070950588259594705,
  "open_price": 0.7486,
  "high_price": 0.7486,
  "low_price": 0.7465,
  "close_price": 0.7465,
  "volume": 1700
}