{
  "symbol": "LAWR",
  "timestamp": "2025-07-18T15:38:00",
  "current_price": 3.57,
  "orb_high": 4.41,
  "orb_low": 3.819,
  "orb_range": 0.5910000000000002,
  "orb_midpoint": 4.1145,
  "breakout_type": "bearish_breakdown",
  "breakout_percentage": 6.520031421838181,
  "volume_ratio": 2.4928922355852157,
  "confidence_score": 0.8522536854679984,
  "priority": "HIGH",
  "confidence_level": "VERY_HIGH",
  "recommended_stop_loss": 3.8377499999999998,
  "recommended_take_profit": 3.4271999999999996,
  "alert_message": "[15:38:00] ORB ALERT: LAWR \u2193 $3.57 (+6.52% vs ORB Low)\nVolume: 2.5x avg | Confidence: 0.85 | Priority: HIGH | EMA9: $3.60 | EMA20: $3.58 | EMA9\u2191EMA20 | Div: +0.6%\nStop: $3.84 | Target: $3.43",
  "ema_9": 3.5977623154165244,
  "ema_20": 3.576859136082485,
  "ema_9_above_20": true,
  "ema_9_below_20": false,
  "ema_divergence": 0.005844004065794233,
  "open_price": null,
  "high_price": null,
  "low_price": null,
  "close_price": null,
  "volume": 10140
}