{
  "symbol": "OPEN",
  "timestamp": "2025-07-22T11:05:00",
  "current_price": 3.19,
  "orb_high": 3.99,
  "orb_low": 3.62,
  "orb_range": 0.3700000000000001,
  "orb_midpoint": 3.805,
  "breakout_type": "bearish_breakdown",
  "breakout_percentage": 11.878453038674037,
  "volume_ratio": 1.598542092902999,
  "confidence_score": 0.8368089030455526,
  "priority": "MEDIUM",
  "confidence_level": "HIGH",
  "recommended_stop_loss": 3.4292499999999997,
  "recommended_take_profit": 3.0624,
  "alert_message": "[11:05:00] ORB ALERT: OPEN \u2193 $3.19 (+11.88% vs ORB Low)\nVolume: 1.6x avg | Confidence: 0.84 | Priority: MEDIUM | EMA9: $3.28 | EMA20: $3.31 | EMA9\u2193EMA20 | Div: -0.9%\nStop: $3.43 | Target: $3.06",
  "ema_9": 3.283446244560797,
  "ema_20": 3.31306013293326,
  "ema_9_above_20": false,
  "ema_9_below_20": true,
  "ema_divergence": -0.008938530296534039,
  "open_price": 3.29,
  "high_price": 3.29,
  "low_price": 3.145,
  "close_price": 3.19,
  "volume": 104281
}