{
  "symbol": "PROK",
  "timestamp": "2025-07-09T11:23:00",
  "current_price": 4.595,
  "orb_high": 6.43,
  "orb_low": 5.34,
  "orb_range": 1.0899999999999999,
  "orb_midpoint": 5.885,
  "breakout_type": "bearish_breakdown",
  "breakout_percentage": 13.951310861423224,
  "volume_ratio": 1.9815212287879804,
  "confidence_score": 0.8415228214310443,
  "priority": "MEDIUM",
  "confidence_level": "HIGH",
  "recommended_stop_loss": 4.9396249999999995,
  "recommended_take_profit": 4.4112,
  "alert_message": "[11:23:00] ORB ALERT: PROK \u2193 $4.59 (+13.95% vs ORB Low)\nVolume: 2.0x avg | Confidence: 0.84 | Priority: MEDIUM\nStop: $4.94 | Target: $4.41"
}