{
  "symbol": "RXRX",
  "timestamp": "2025-07-23T13:13:00",
  "current_price": 6.29,
  "orb_high": 7.14,
  "orb_low": 6.63,
  "orb_range": 0.5099999999999998,
  "orb_midpoint": 6.885,
  "breakout_type": "bearish_breakdown",
  "breakout_percentage": 5.128205128205126,
  "volume_ratio": 2.279970255484145,
  "confidence_score": 0.8188910597690193,
  "priority": "MEDIUM",
  "confidence_level": "HIGH",
  "recommended_stop_loss": 6.76175,
  "recommended_take_profit": 6.0384,
  "alert_message": "[13:13:00] ORB ALERT: RXRX \u2193 $6.29 (+5.13% vs ORB Low)\nVolume: 2.3x avg | Confidence: 0.82 | Priority: MEDIUM | EMA9: $6.34 | EMA20: $6.36 | EMA9\u2193EMA20 | Div: -0.4%\nStop: $6.76 | Target: $6.04",
  "ema_9": 6.336697008632926,
  "ema_20": 6.3611640063371935,
  "ema_9_above_20": false,
  "ema_9_below_20": true,
  "ema_divergence": -0.003846308266834856,
  "open_price": 6.3,
  "high_price": 6.3,
  "low_price": 6.29,
  "close_price": 6.29,
  "volume": 5050
}