{
  "symbol": "SOWG",
  "timestamp": "2025-07-25T15:56:00",
  "current_price": 1.55,
  "orb_high": 1.9799,
  "orb_low": 1.63,
  "orb_range": 0.3499000000000001,
  "orb_midpoint": 1.8049499999999998,
  "breakout_type": "bearish_breakdown",
  "breakout_percentage": 4.907975460122691,
  "volume_ratio": 1.5172588190668859,
  "confidence_score": 0.8273280198201223,
  "priority": "MEDIUM",
  "confidence_level": "HIGH",
  "recommended_stop_loss": 1.66625,
  "recommended_take_profit": 1.488,
  "alert_message": "[15:56:00] ORB ALERT: SOWG \u2193 $1.55 (+4.91% vs ORB Low)\nVolume: 1.5x avg | Confidence: 0.83 | Priority: MEDIUM | EMA9: $1.53 | EMA20: $1.52 | EMA9\u2191EMA20 | Div: +1.0%\nStop: $1.67 | Target: $1.49",
  "ema_9": 1.5321168156976746,
  "ema_20": 1.517555724081014,
  "ema_9_above_20": true,
  "ema_9_below_20": false,
  "ema_divergence": 0.009595095182075297,
  "open_price": 1.55,
  "high_price": 1.55,
  "low_price": 1.54,
  "close_price": 1.55,
  "volume": 400
}