{
  "symbol": "SDST",
  "timestamp": "2025-07-14T10:56:00",
  "alert_type": "super_alert",
  "trigger_condition": "signal_price_reached",
  "original_alert": {
    "symbol": "SDST",
    "timestamp": "2025-07-14T10:56:00",
    "current_price": 0.6031,
    "orb_high": 0.5284,
    "orb_low": 0.4503,
    "orb_range": 0.0781,
    "orb_midpoint": 0.48934999999999995,
    "breakout_type": "bullish_breakout",
    "breakout_percentage": 14.137017411052232,
    "volume_ratio": 3.0356809775723663,
    "confidence_score": 0.9369019468366673,
    "priority": "HIGH",
    "confidence_level": "VERY_HIGH",
    "recommended_stop_loss": 0.5578675,
    "recommended_take_profit": 0.627224,
    "alert_message": "[10:56:00] ORB ALERT: SDST \u2191 $0.60 (+14.14% vs ORB High)\nVolume: 3.0x avg | Confidence: 0.94 | Priority: HIGH\nStop: $0.56 | Target: $0.63"
  },
  "signal_analysis": {
    "signal_price": 0.55,
    "resistance_price": 0.69,
    "current_price": 0.6031,
    "penetration_percent": 37.93,
    "range_percent": 1.25,
    "signal_reached": true,
    "resistance_reached": false
  },
  "metrics": {
    "signal_to_resistance_range": 0.1399999999999999,
    "price_above_signal": 0.053099999999999925,
    "distance_to_resistance": 0.08689999999999998
  },
  "risk_assessment": {
    "entry_price": 0.55,
    "target_price": 0.69,
    "current_risk_reward": 1.6365348399246724
  }
}