{
  "symbol": "CLDI",
  "timestamp": "2025-07-09T11:47:00",
  "current_price": 1.225,
  "orb_high": 0.9357,
  "orb_low": 0.7528,
  "orb_range": 0.18289999999999995,
  "orb_midpoint": 0.84425,
  "breakout_type": "bullish_breakout",
  "breakout_percentage": 30.91802928288983,
  "volume_ratio": 1.726691535858907,
  "confidence_score": 0.8898828467447499,
  "priority": "MEDIUM",
  "confidence_level": "VERY_HIGH",
  "recommended_stop_loss": 1.1331250000000002,
  "recommended_take_profit": 1.2740000000000002,
  "alert_message": "[11:47:00] ORB ALERT: CLDI \u2191 $1.23 (+30.92% vs ORB High)\nVolume: 1.7x avg | Confidence: 0.89 | Priority: MEDIUM\nStop: $1.13 | Target: $1.27"
}