{
  "symbol": "DFLI",
  "timestamp": "2025-07-22T13:16:00",
  "current_price": 0.5579,
  "orb_high": 0.52,
  "orb_low": 0.4035,
  "orb_range": 0.11649999999999999,
  "orb_midpoint": 0.46175,
  "breakout_type": "bullish_breakout",
  "breakout_percentage": 7.288461538461526,
  "volume_ratio": 1.7283194675540765,
  "confidence_score": 0.8784672477680646,
  "priority": "MEDIUM",
  "confidence_level": "VERY_HIGH",
  "recommended_stop_loss": 0.5160575,
  "recommended_take_profit": 0.580216,
  "alert_message": "[13:16:00] ORB ALERT: DFLI \u2191 $0.56 (+7.29% vs ORB High)\nVolume: 1.7x avg | Confidence: 0.88 | Priority: MEDIUM | EMA9: $0.55 | EMA20: $0.54 | EMA9\u2191EMA20 | Div: +2.1%\nStop: $0.52 | Target: $0.58",
  "ema_9": 0.5469273799535805,
  "ema_20": 0.5354412839200701,
  "ema_9_above_20": true,
  "ema_9_below_20": false,
  "ema_divergence": 0.021451644425731473,
  "open_price": 0.5596,
  "high_price": 0.5605,
  "low_price": 0.5579,
  "close_price": 0.5579,
  "volume": 7574
}