{
  "symbol": "IXHL",
  "timestamp": "2025-07-15T13:32:00",
  "current_price": 0.3632,
  "orb_high": 0.2575,
  "orb_low": 0.25,
  "orb_range": 0.007500000000000007,
  "orb_midpoint": 0.25375000000000003,
  "breakout_type": "bullish_breakout",
  "breakout_percentage": 41.0485436893204,
  "volume_ratio": 3.4818706559345083,
  "confidence_score": 0.844089354224799,
  "priority": "MEDIUM",
  "confidence_level": "HIGH",
  "recommended_stop_loss": 0.33596000000000004,
  "recommended_take_profit": 0.37772800000000006,
  "alert_message": "[13:32:00] ORB ALERT: IXHL \u2191 $0.36 (+41.05% vs ORB High)\nVolume: 3.5x avg | Confidence: 0.84 | Priority: MEDIUM\nStop: $0.34 | Target: $0.38"
}