{
  "symbol": "MCVT",
  "timestamp": "2025-07-25T11:59:00",
  "current_price": 4.125,
  "orb_high": 2.9099,
  "orb_low": 2.44,
  "orb_range": 0.4699,
  "orb_midpoint": 2.67495,
  "breakout_type": "bullish_breakout",
  "breakout_percentage": 41.75744870957765,
  "volume_ratio": 2.199703654922621,
  "confidence_score": 0.9027299790896233,
  "priority": "HIGH",
  "confidence_level": "VERY_HIGH",
  "recommended_stop_loss": 3.8156250000000003,
  "recommended_take_profit": 4.29,
  "alert_message": "[11:59:00] ORB ALERT: MCVT \u2191 $4.12 (+41.76% vs ORB High)\nVolume: 2.2x avg | Confidence: 0.90 | Priority: HIGH | EMA9: $3.76 | EMA20: $3.54 | EMA9\u2191EMA20 | Div: +6.3%\nStop: $3.82 | Target: $4.29",
  "ema_9": 3.762181580780354,
  "ema_20": 3.5405688905273722,
  "ema_9_above_20": true,
  "ema_9_below_20": false,
  "ema_divergence": 0.06259239605417544,
  "open_price": 4.14,
  "high_price": 4.18,
  "low_price": 4.07,
  "close_price": 4.125,
  "volume": 3879
}