{
  "symbol": "MCVT",
  "timestamp": "2025-07-25T11:50:00",
  "current_price": 3.29,
  "orb_high": 2.9099,
  "orb_low": 2.44,
  "orb_range": 0.4699,
  "orb_midpoint": 2.67495,
  "breakout_type": "bullish_breakout",
  "breakout_percentage": 13.062304546547995,
  "volume_ratio": 2.9218071242397916,
  "confidence_score": 0.9102823085883085,
  "priority": "HIGH",
  "confidence_level": "VERY_HIGH",
  "recommended_stop_loss": 3.04325,
  "recommended_take_profit": 3.4216,
  "alert_message": "[11:50:00] ORB ALERT: MCVT \u2191 $3.29 (+13.06% vs ORB High)\nVolume: 2.9x avg | Confidence: 0.91 | Priority: HIGH | EMA9: $3.39 | EMA20: $3.24 | EMA9\u2191EMA20 | Div: +4.6%\nStop: $3.04 | Target: $3.42",
  "ema_9": 3.3891274069275457,
  "ema_20": 3.239604682138846,
  "ema_9_above_20": true,
  "ema_9_below_20": false,
  "ema_divergence": 0.046154620535361825,
  "open_price": 3.44,
  "high_price": 3.44,
  "low_price": 3.23,
  "close_price": 3.29,
  "volume": 4425
}