{
  "symbol": "NAK",
  "timestamp": "2025-07-18T15:31:00",
  "current_price": 1.03,
  "orb_high": 1.01,
  "orb_low": 0.83,
  "orb_range": 0.18000000000000005,
  "orb_midpoint": 0.9199999999999999,
  "breakout_type": "bullish_breakout",
  "breakout_percentage": 1.980198019801982,
  "volume_ratio": 2.817119635545153,
  "confidence_score": 0.8993440082953791,
  "priority": "HIGH",
  "confidence_level": "VERY_HIGH",
  "recommended_stop_loss": 0.9527500000000001,
  "recommended_take_profit": 1.0712000000000002,
  "alert_message": "[15:31:00] ORB ALERT: NAK \u2191 $1.03 (+1.98% vs ORB High)\nVolume: 2.8x avg | Confidence: 0.90 | Priority: HIGH | EMA9: $1.05 | EMA20: $1.05 | EMA9\u2193EMA20 | Div: -0.3%\nStop: $0.95 | Target: $1.07",
  "ema_9": 1.0498277743328808,
  "ema_20": 1.053096670313516,
  "ema_9_above_20": false,
  "ema_9_below_20": true,
  "ema_divergence": -0.003104079684975274,
  "open_price": null,
  "high_price": null,
  "low_price": null,
  "close_price": null,
  "volume": 409223
}