{
  "symbol": "OCTO",
  "timestamp": "2025-07-25T15:42:00",
  "current_price": 2.5,
  "orb_high": 1.98,
  "orb_low": 1.81,
  "orb_range": 0.16999999999999993,
  "orb_midpoint": 1.895,
  "breakout_type": "bullish_breakout",
  "breakout_percentage": 26.262626262626267,
  "volume_ratio": 2.1294021294021293,
  "confidence_score": 0.8903463638973471,
  "priority": "HIGH",
  "confidence_level": "VERY_HIGH",
  "recommended_stop_loss": 2.3125,
  "recommended_take_profit": 2.6,
  "alert_message": "[15:42:00] ORB ALERT: OCTO \u2191 $2.50 (+26.26% vs ORB High)\nVolume: 2.1x avg | Confidence: 0.89 | Priority: HIGH | EMA9: $2.40 | EMA20: $2.31 | EMA9\u2191EMA20 | Div: +3.5%\nStop: $2.31 | Target: $2.60",
  "ema_9": 2.3958775746904846,
  "ema_20": 2.3139445804720022,
  "ema_9_above_20": true,
  "ema_9_below_20": false,
  "ema_divergence": 0.03540836496687812,
  "open_price": 2.45,
  "high_price": 2.5,
  "low_price": 2.45,
  "close_price": 2.5,
  "volume": 1300
}