{
  "symbol": "OPEN",
  "timestamp": "2025-07-16T15:16:00",
  "current_price": 1.445,
  "orb_high": 1.29,
  "orb_low": 1.145,
  "orb_range": 0.14500000000000002,
  "orb_midpoint": 1.2175,
  "breakout_type": "bullish_breakout",
  "breakout_percentage": 12.015503875968994,
  "volume_ratio": 2.25808179963796,
  "confidence_score": 0.8881935157741354,
  "priority": "HIGH",
  "confidence_level": "VERY_HIGH",
  "recommended_stop_loss": 1.3366250000000002,
  "recommended_take_profit": 1.5028000000000001,
  "alert_message": "[15:16:00] ORB ALERT: OPEN \u2191 $1.45 (+12.02% vs ORB High)\nVolume: 2.3x avg | Confidence: 0.89 | Priority: HIGH | EMA9: $1.43 | EMA20: $1.42 | EMA9\u2191EMA20 | Div: +0.8%\nStop: $1.34 | Target: $1.50",
  "ema_9": 1.4336323556299388,
  "ema_20": 1.4228399850079994,
  "ema_9_above_20": true,
  "ema_9_below_20": false,
  "ema_divergence": 0.007585090899648016
}